fitk/VERSION.txt
fitk/__init__.py
fitk/derivatives.py
fitk/graphics.py
fitk/interfaces/__init__.py
fitk/interfaces/camb_interfaces.py
fitk/interfaces/classy_interfaces.py
fitk/interfaces/coffe_interfaces.py
fitk/interfaces/misc_interfaces.py
fitk/operations.py
fitk/tensors.py
fitk/utilities.py
fitk-0.11.1.dist-info/LICENSE
fitk-0.11.1.dist-info/METADATA
fitk-0.11.1.dist-info/WHEEL
fitk-0.11.1.dist-info/RECORD
