Metadata-Version: 2.1
Name: fitk
Version: 0.11.1
Summary: The Fisher Information ToolKit
Home-page: https://github.com/JCGoran/fitk/
License: MIT
Author: JCGoran
Author-email: goran.jelic-cizmek@unige.ch
Requires-Python: >=3.7,<4
Classifier: License :: OSI Approved :: MIT License
Classifier: Programming Language :: Python :: 3
Classifier: Programming Language :: Python :: 3.7
Classifier: Programming Language :: Python :: 3.8
Classifier: Programming Language :: Python :: 3.9
Classifier: Programming Language :: Python :: 3.10
Classifier: Programming Language :: Python :: 3.11
Provides-Extra: camb
Provides-Extra: classy
Provides-Extra: coffe
Provides-Extra: interfaces
Requires-Dist: camb ; extra == "camb" or extra == "interfaces"
Requires-Dist: classy ; extra == "classy" or extra == "interfaces"
Requires-Dist: coffe ; extra == "coffe" or extra == "interfaces"
Requires-Dist: matplotlib (==3.5.3) ; python_version == "3.7"
Requires-Dist: matplotlib (>3.5.3) ; python_version >= "3.8"
Requires-Dist: numpy (==1.21.6) ; python_version == "3.7"
Requires-Dist: numpy (>1.22) ; python_version >= "3.8"
Requires-Dist: scipy (==1.7.3) ; python_version == "3.7"
Requires-Dist: scipy (>1.7.3) ; python_version >= "3.8"
Requires-Dist: sympy
Project-URL: Documentation, https://jcgoran.github.io/fitk/
Project-URL: Repository, https://github.com/JCGoran/fitk/
